lair/__init__.py
lair/f2f.py
lair/g_game.py
lair/odeve.py
lair/rps.py
mylair-0.0.2.dist-info/licenses/LICENSE.txt
mylair-0.0.2.dist-info/METADATA
mylair-0.0.2.dist-info/WHEEL
mylair-0.0.2.dist-info/top_level.txt
mylair-0.0.2.dist-info/RECORD
