Metadata-Version: 2.4
Name: mylair
Version: 0.0.2
Summary: A collection of fun terminal games (Odd/Even, RPS, Guess Number, etc.)
Author-email: Arhan Ali <arhanali7943@gmail.com>
License-Expression: MIT
Project-URL: Homepage, https://pypi.org/project/mylair/
Requires-Python: >=3.7
License-File: LICENSE.txt
Dynamic: license-file
